rdm/__init__.py
rdm/helpers.py
rdm/validation.py
rdm/db/__init__.py
rdm/db/context.py
rdm/db/converters.py
rdm/db/datasource.py
rdm/db/interaction_views.py
rdm/db/library.py
rdm/db/mapper.pl
rdm/db/mapper.py
rdm/db/migration.py
rdm/db/urls.py
rdm/db/views.py
rdm/db/visualization_views.py
rdm/db/package_data/categories/b349a089-0af7-4d86-838b-e8c93d9d6ca5.json
rdm/db/package_data/categories/b66b71b1-99d6-4efc-b264-a914a3e42911.json
rdm/db/package_data/categories/ed859be5-cc13-46b9-b249-c8f026732c1c.json
rdm/db/package_data/widgets/3c5ac714-84ca-4c93-befb-ce0c16148193.json
rdm/db/package_data/widgets/3f41052d-df1f-44b5-83c0-37ce70d86259.json
rdm/db/package_data/widgets/41978deb-c245-4e1f-95a2-ceadcfe6898a.json
rdm/db/package_data/widgets/50f8a9cf-046c-43e9-9681-d700cbbbb689.json
rdm/db/package_data/widgets/649015ac-ca53-43bc-a36a-c603b52f8775.json
rdm/db/package_data/widgets/6c168f2e-e47f-409a-97c1-58d50fbbec4d.json
rdm/db/package_data/widgets/773d5469-eb3d-4c16-9554-260f1f73ec31.json
rdm/db/package_data/widgets/804af24c-cecf-4296-85f5-798a45b7a0a8.json
rdm/db/package_data/widgets/b07e0349-3d50-42b2-9678-dc7752b44d7e.json
rdm/db/package_data/widgets/b8dcd7bf-cfed-42e0-8bf9-02149c499f1e.json
rdm/db/package_data/widgets/baa32a60-5acb-42a1-ba83-23a6ab2160e7.json
rdm/db/package_data/widgets/e5b68e38-cb53-408a-a58f-26742d6ecb3c.json
rdm/db/static/rdm.db/icons/treeview/construction_work .png
rdm/db/static/rdm.db/icons/treeview/database.png
rdm/db/static/rdm.db/icons/widget/construction_work .png
rdm/db/static/rdm.db/icons/widget/database.png
rdm/db/static/rdm.db/js/jquery-1.7.1.min.js
rdm/db/templates/interactions/db_context.html
rdm/db/templates/interactions/orange_converter.html
rdm/wrappers/__init__.py
rdm/wrappers/interaction_views.py
rdm/wrappers/library.py
rdm/wrappers/migration.py
rdm/wrappers/security.py
rdm/wrappers/urls.py
rdm/wrappers/views.py
rdm/wrappers/visualization_views.py
rdm/wrappers/aleph/__init__.py
rdm/wrappers/aleph/aleph.pl
python_rdm-0.3.7.dist-info/LICENSE.md
python_rdm-0.3.7.dist-info/METADATA
python_rdm-0.3.7.dist-info/WHEEL
python_rdm-0.3.7.dist-info/top_level.txt
python_rdm-0.3.7.dist-info/RECORD
