Metadata-Version: 2.1
Name: python-rdm
Version: 0.3.7
Summary: Relational data mining in python
Home-page: https://github.com/xflows/rdm
Author: Anze Vavpetic
Author-email: anze.vavpetic@ijs.si
License: MIT License
Classifier: Development Status :: 2 - Pre-Alpha
Classifier: Environment :: Web Environment
Classifier: Framework :: Django
Classifier: Intended Audience :: Developers
Classifier: License :: OSI Approved :: MIT License
Classifier: Operating System :: OS Independent
Classifier: Programming Language :: Python
Classifier: Programming Language :: Python :: 3
Classifier: Programming Language :: Prolog
Classifier: Topic :: Internet :: WWW/HTTP
Classifier: Topic :: Internet :: WWW/HTTP :: Dynamic Content
Classifier: Topic :: Scientific/Engineering :: Artificial Intelligence
Classifier: Topic :: Software Development :: Libraries
License-File: LICENSE.md
Requires-Dist: PyMySQL
Requires-Dist: psycopg2-binary
Requires-Dist: liac-arff
Requires-Dist: Orange3 (==3.26.0)
Provides-Extra: dev
Requires-Dist: Sphinx ; extra == 'dev'
Requires-Dist: sphinx-rtd-theme ; extra == 'dev'
